odoo/addons/l10n_ch_zip/README.rst
odoo/addons/l10n_ch_zip/__init__.py
odoo/addons/l10n_ch_zip/__manifest__.py
odoo/addons/l10n_ch_zip/hooks.py
odoo/addons/l10n_ch_zip/data/res.city.csv
odoo/addons/l10n_ch_zip/data/res.city.zip.csv
odoo/addons/l10n_ch_zip/i18n/de.po
odoo/addons/l10n_ch_zip/i18n/fr.po
odoo/addons/l10n_ch_zip/i18n/it.po
odoo/addons/l10n_ch_zip/i18n/l10n_ch_zip.pot
odoo/addons/l10n_ch_zip/models/__init__.py
odoo/addons/l10n_ch_zip/models/city_zip.py
odoo/addons/l10n_ch_zip/readme/CONTRIBUTORS.rst
odoo/addons/l10n_ch_zip/readme/DESCRIPTION.rst
odoo/addons/l10n_ch_zip/readme/INSTALL.rst
odoo/addons/l10n_ch_zip/readme/USAGE.rst
odoo/addons/l10n_ch_zip/static/description/icon.png
odoo/addons/l10n_ch_zip/static/description/index.html
odoo12_addon_l10n_ch_zip-12.0.1.0.0.99.dev7.dist-info/METADATA
odoo12_addon_l10n_ch_zip-12.0.1.0.0.99.dev7.dist-info/WHEEL
odoo12_addon_l10n_ch_zip-12.0.1.0.0.99.dev7.dist-info/top_level.txt
odoo12_addon_l10n_ch_zip-12.0.1.0.0.99.dev7.dist-info/RECORD
