Metadata-Version: 2.1
Name: odoo12-addon-l10n-ch-zip
Version: 12.0.1.0.0.99.dev7
Summary: Provides all Swiss postal codes for auto-completion
Home-page: http://www.camptocamp.com
Author: Camptocamp, brain-tec AG, copadoMEDIA UG, Odoo Community Association (OCA)
Author-email: support@odoo-community.org
License: AGPL-3
Platform: UNKNOWN
Classifier: Programming Language :: Python
Classifier: Framework :: Odoo
Classifier: Framework :: Odoo :: 12.0
Classifier: License :: OSI Approved :: GNU Affero General Public License v3
Requires-Python: >=3.5
Requires-Dist: odoo12-addon-base-location
Requires-Dist: odoo12-addon-l10n-ch-states
Requires-Dist: odoo <12.1dev,>=12.0a
